mmaction/__init__.py
mmaction/registry.py
mmaction/version.py
mmaction/.mim/dataset-index.yml
mmaction/.mim/model-index.yml
mmaction/.mim/configs/_base_/default_runtime.py
mmaction/.mim/configs/_base_/models/audioonly_r50.py
mmaction/.mim/configs/_base_/models/bmn_400x100.py
mmaction/.mim/configs/_base_/models/bsn_pem.py
mmaction/.mim/configs/_base_/models/bsn_tem.py
mmaction/.mim/configs/_base_/models/c2d_r50.py
mmaction/.mim/configs/_base_/models/c3d_sports1m_pretrained.py
mmaction/.mim/configs/_base_/models/i3d_r50.py
mmaction/.mim/configs/_base_/models/ircsn_r152.py
mmaction/.mim/configs/_base_/models/mvit_small.py
mmaction/.mim/configs/_base_/models/r2plus1d_r34.py
mmaction/.mim/configs/_base_/models/slowfast_r50.py
mmaction/.mim/configs/_base_/models/slowonly_r50.py
mmaction/.mim/configs/_base_/models/swin_tiny.py
mmaction/.mim/configs/_base_/models/tanet_r50.py
mmaction/.mim/configs/_base_/models/tin_r50.py
mmaction/.mim/configs/_base_/models/tpn_slowonly_r50.py
mmaction/.mim/configs/_base_/models/tpn_tsm_r50.py
mmaction/.mim/configs/_base_/models/trn_r50.py
mmaction/.mim/configs/_base_/models/tsm_mobilenet_v2.py
mmaction/.mim/configs/_base_/models/tsm_mobileone_s4.py
mmaction/.mim/configs/_base_/models/tsm_r50.py
mmaction/.mim/configs/_base_/models/tsn_mobileone_s0.py
mmaction/.mim/configs/_base_/models/tsn_r50.py
mmaction/.mim/configs/_base_/models/x3d.py
mmaction/.mim/configs/_base_/schedules/adam_20e.py
mmaction/.mim/configs/_base_/schedules/sgd_100e.py
mmaction/.mim/configs/_base_/schedules/sgd_150e_warmup.py
mmaction/.mim/configs/_base_/schedules/sgd_50e.py
mmaction/.mim/configs/_base_/schedules/sgd_tsm_100e.py
mmaction/.mim/configs/_base_/schedules/sgd_tsm_50e.py
mmaction/.mim/configs/_base_/schedules/sgd_tsm_mobilenet_v2_100e.py
mmaction/.mim/configs/_base_/schedules/sgd_tsm_mobilenet_v2_50e.py
mmaction/.mim/configs/detection/acrn/metafile.yml
mmaction2-1.2.0.dist-info/LICENSE
mmaction2-1.2.0.dist-info/METADATA
mmaction2-1.2.0.dist-info/WHEEL
mmaction2-1.2.0.dist-info/top_level.txt
mmaction2-1.2.0.dist-info/RECORD
